.readthedocs.yml
LICENSE
MANIFEST.in
README.md
pyproject.toml
setup.cfg
setup.py
data/stellar/WAVE_PHOENIX-ACES-AGSS-COND-2011.fits
data/stellar/PHOENIX/lte02400-0.50-4.0.PHOENIX-ACES-AGSS-COND-2011-HiRes.fits
data/tellurics/skycalc/almanac_example.txt
data/tellurics/skycalc/skycalc.py
data/tellurics/skycalc/skycalc_cli.py
data/tellurics/skycalc/skycalc_defaults.txt
docs/Makefile
docs/conf.py
docs/index.rst
docs/make.bat
notebooks/00-intro.ipynb
simulacra/__init__.py
simulacra/convolve.py
simulacra/dataset.py
simulacra/detector.py
simulacra/gascell.py
simulacra/lanczos.py
simulacra/simulator.py
simulacra/star.py
simulacra/tellurics.py
simulacra/theory.py
simulacra/version.py
simulacra/__pycache__/__init__.cpython-37.pyc
simulacra/__pycache__/convolve.cpython-37.pyc
simulacra/__pycache__/dataset.cpython-37.pyc
simulacra/__pycache__/detector.cpython-37.pyc
simulacra/__pycache__/gascell.cpython-37.pyc
simulacra/__pycache__/lanczos.cpython-37.pyc
simulacra/__pycache__/star.cpython-37.pyc
simulacra/__pycache__/tellurics.cpython-37.pyc
simulacra/__pycache__/theory.cpython-37.pyc
simulacra/cli/__init__.py
simulacra/cli/main.py
simulacra_spectra.egg-info/PKG-INFO
simulacra_spectra.egg-info/SOURCES.txt
simulacra_spectra.egg-info/dependency_links.txt
simulacra_spectra.egg-info/not-zip-safe
simulacra_spectra.egg-info/requires.txt
simulacra_spectra.egg-info/top_level.txt